parsezeeklogs/__init__.py
parsezeeklogs-2.0.1.dist-info/LICENSE.txt
parsezeeklogs-2.0.1.dist-info/METADATA
parsezeeklogs-2.0.1.dist-info/WHEEL
parsezeeklogs-2.0.1.dist-info/top_level.txt
parsezeeklogs-2.0.1.dist-info/RECORD
