Metadata-Version: 2.1
Name: parsezeeklogs
Version: 2.0.1
Summary: A lightweight utility for programmatically reading and manipulating Zeek IDS (Bro IDS) log files and outputting into JSON or CSV format.
Home-page: https://github.com/dgunter/parsezeeklogs
Author: Dan Gunter
Author-email: dangunter@gmail.com
License: UNKNOWN
Download-URL: https://github.com/dgunter/parsezeeklogs/archive/v1.1.3.tar.gz
Keywords: InfoSec,Bro IDS,security
Platform: UNKNOWN
Classifier: License :: OSI Approved :: MIT License
Classifier: Operating System :: OS Independent
